slack_primitive_cli/__init__.py
slack_primitive_cli/__main__.py
slack_primitive_cli/__version__.py
slack_primitive_cli/command/__init__.py
slack_primitive_cli/command/chat.py
slack_primitive_cli/command/files.py
slack_primitive_cli/common/__init__.py
slack_primitive_cli/common/utils.py
slack_primitive_cli-0.3.0.dist-info/LICENSE
slack_primitive_cli-0.3.0.dist-info/METADATA
slack_primitive_cli-0.3.0.dist-info/WHEEL
slack_primitive_cli-0.3.0.dist-info/entry_points.txt
slack_primitive_cli-0.3.0.dist-info/RECORD
