Metadata-Version: 2.1
Name: slack-primitive-cli
Version: 0.3.0
Summary: Primitive Slack CLI
Home-page: https://github.com/kurusugawa-computer/slack-primitive-cli
License: MIT
Keywords: slack,cli
Author: Kurusugawa Computer Inc.
Requires-Python: >=3.9,<4.0
Classifier: Development Status :: 2 - Pre-Alpha
Classifier: Intended Audience :: Developers
Classifier: License :: OSI Approved :: MIT License
Classifier: Operating System :: OS Independent
Classifier: Programming Language :: Python :: 3
Classifier: Programming Language :: Python :: 3.9
Classifier: Programming Language :: Python :: 3.10
Classifier: Programming Language :: Python :: 3.11
Classifier: Topic :: Utilities
Requires-Dist: backoff
Requires-Dist: click (>=8,<9)
Requires-Dist: click-option-group
Requires-Dist: slack-sdk (>=3,<4)
Project-URL: Repository, https://github.com/kurusugawa-computer/slack-primitive-cli
